commitwise/__init__.py
commitwise/ai_source.py
commitwise/cli.py
commitwise/cli_utils.py
commitwise/config.py
commitwise/errors.py
commitwise/file_source.py
commitwise/git_utils.py
commitwise/ai/__init__.py
commitwise/ai/base.py
commitwise/ai/local_engine.py
commitwise/ai/openai_engine.py
commitwise-0.1.6.dist-info/licenses/LICENSE
commitwise-0.1.6.dist-info/METADATA
commitwise-0.1.6.dist-info/WHEEL
commitwise-0.1.6.dist-info/entry_points.txt
commitwise-0.1.6.dist-info/top_level.txt
commitwise-0.1.6.dist-info/RECORD
