Metadata-Version: 2.4
Name: commitwise
Version: 0.1.6
Summary: Generate clean git commit messages from files or AI
Author-email: Abolfazl Hassan Zade <abolfazl.hassanzade.81@gmail.com>
License: MIT
Project-URL: homepage, https://github.com/hasssan-hasssan/commitwise
Project-URL: repository, https://github.com/hasssan-hasssan/commitwise
Project-URL: issues, https://github.com/hasssan-hasssan/commitwise/issues
Keywords: git,commit,cli,ai
Requires-Python: >=3.9
License-File: LICENSE
Requires-Dist: requests>=2.31.0
Dynamic: license-file
